koldstart/__init__.py
koldstart/api.py
koldstart/auth/__init__.py
koldstart/auth/auth0.py
koldstart/auth/local.py
koldstart/cli.py
koldstart/console/__init__.py
koldstart/console/icons.py
koldstart/console/ux.py
koldstart/exceptions/__init__.py
koldstart/exceptions/_base.py
koldstart/exceptions/auth.py
koldstart/exceptions/handlers.py
koldstart/flags.py
koldstart/logging/__init__.py
koldstart/logging/datadog.py
koldstart/logging/isolate.py
koldstart/logging/style.py
koldstart/logging/trace.py
koldstart/logging/user.py
koldstart/sdk.py
koldstart-0.6.23.dist-info/entry_points.txt
koldstart-0.6.23.dist-info/WHEEL
koldstart-0.6.23.dist-info/METADATA
koldstart-0.6.23.dist-info/RECORD
